nonebot_plugin_lisenter
